main/drawtime.py
drawtime-0.9.dist-info/METADATA
drawtime-0.9.dist-info/WHEEL
drawtime-0.9.dist-info/top_level.txt
drawtime-0.9.dist-info/RECORD
