Metadata-Version: 2.1
Name: drawtime
Version: 0.9
Summary: this is superset of turtle module in python
Home-page: UNKNOWN
Author: anocoder
License: UNKNOWN
Platform: UNKNOWN
